{
  "error_id": "error_20251113_115456_0150",
  "timestamp": "2025-11-13T11:54:56.666154",
  "pdf_name": "e4b3e21e-bad4-489c-bd98-1fc3c780c9ec",
  "page_number": 397,
  "error_type": "missing_field",
  "error_message": "Campo 'mresumen' está vacío o no se pudo extraer",
  "context": {
    "field_name": "mresumen",
    "expected_value": "Lista de items de resumen"
  },
  "extracted_data": {
    "midioma": [
      {
        "iMIdioma": 2,
        "tIdioma": "Inglés"
      }
    ],
    "mdocumento_tipo": [
      {
        "iMDocumentoTipo": 2,
        "tTipo": "Resumen"
      }
    ],
    "mdivisa": [
      {
        "tDivisa": "USD"
      }
    ],
    "mnaturaleza": [
      {
        "tNaturaleza": "Otro"
      }
    ],
    "mproveedor": [
      {
        "tRazonSocial": "PLEASE UPDATE TO WORKCARE"
      }
    ]
  },
  "ocr_text_length": 3212,
  "ocr_text_preview": "OTHBP\nOE0087\nPLEASE UPDATE TO WORKCARE'S NEW BANKING INFORMATION LISTED BELOW\n03/04/2025: International Misc. Testing [New Delhi, India] 1 484.06 $484.06\nPrzemyslaw Mazur\n03/04/2025: International 11 Panel Drug Screen - Preplacement 1 0.00 $0.00\n[New Delhi, India]\nPrzemyslaw Mazur\n03/04/2025: International Alcohol Test [New Delhi, India] 1 0.00 $0.00\nPrzemyslaw Mazur\n03/04/2025: Review Exam Provided by Others (I) [New Delhi, 1 138.00 $138.00\nIndia]\nPrzemyslaw Mazur\n03/04/2025: Management Fee Int",
  "ocr_text_file": "C:\\Users\\Soporte\\Documents\\Proyectos\\ExtractorOCRv1\\learning\\errors\\error_20251113_115456_0150_ocr_text.txt"
}