{
  "error_id": "error_20251111_160731_0090",
  "timestamp": "2025-11-11T16:07:31.743690",
  "pdf_name": "82c0c2a9-085c-4328-a42b-3a9e6d73e0b2",
  "page_number": 126,
  "error_type": "missing_field",
  "error_message": "Campo 'tNumero' está vacío o no se pudo extraer",
  "context": {
    "field_name": "tNumero",
    "expected_value": null
  },
  "extracted_data": {
    "comprobante": {
      "_stamp_name": "BSQE",
      "_sequential_number": "BS2025",
      "tSerie": null,
      "tCliente": null
    }
  },
  "ocr_text_length": 646,
  "ocr_text_preview": "Invoice No. Report/Emp Number Technical Specialist Supplier Supplier PO Country PPE / Date Date Period Charge No/Sub No Units Type Rate Total Curr\nBSQE AUSTRALIA ENTRIES\nEntries in Jun 2025:\nAmount Hours\nE9XL 0000 890 24084 PAY AUD$ (112,592.00)\nE9XL M&M 890 26629 310 AUD$ 2,618.00 17.0\nE9XL M&M 890 26439 712 AUD$ 77,298.00 499.50\nE9XL M&M 890 26711 110 AUD$ 15,736.00 101.50\nE9XL Energy 890 26232 115 AUD$ 16,940.00 110.00\n0.00 728.0\nE9XL M&M 24084 PAY USD$ (2,600.00)\nE9XL M&M 890 26251 140 USD$\n",
  "ocr_text": "Invoice No. Report/Emp Number Technical Specialist Supplier Supplier PO Country PPE / Date Date Period Charge No/Sub No Units Type Rate Total Curr\nBSQE AUSTRALIA ENTRIES\nEntries in Jun 2025:\nAmount Hours\nE9XL 0000 890 24084 PAY AUD$ (112,592.00)\nE9XL M&M 890 26629 310 AUD$ 2,618.00 17.0\nE9XL M&M 890 26439 712 AUD$ 77,298.00 499.50\nE9XL M&M 890 26711 110 AUD$ 15,736.00 101.50\nE9XL Energy 890 26232 115 AUD$ 16,940.00 110.00\n0.00 728.0\nE9XL M&M 24084 PAY USD$ (2,600.00)\nE9XL M&M 890 26251 140 USD$\nE9XL M&M 890 26442 223 USD$ 2,600.00 26.0\n- 26.0\ncost of invoice is recorded to 24084 PAY & EXP when invoice is recorded\nJob charge will autocode."
}